Workbook

Sheet Movimientos
A1: Fecha | B1: Comercio | C1: Categoría | D1: Tipo | E1: Importe | F1: Saldo
A2: 46142 | B2: Pastelería La Mallorquina | C2: Comida fuera | D2: compra | E2: -3.2 | F2: 982
A3: 46142 | B3: Mercadona | C3: Supermercado | D3: compra | E3: -55.2 | F3: 985.2
A4: 46141 | B4: Movistar España | C4: Hogar (suministros) | D4: compra | E4: -49.9 | F4: 1040.4
A5: 46140 | B5: Ana García López | C5: Transferencias personales | D5: transferencia entrada | E5: 100 | F5: 1090.3
A6: 46139 | B6: Mercadona | C6: Supermercado | D6: compra | E6: -64.3 | F6: 990.3
A7: 46138 | B7: Disney Plus | C7: Suscripciones | D7: suscripción | E7: -8.99 | F7: 1054.6
A8: 46138 | B8: Decathlon Alcobendas | C8: Ocio | D8: compra | E8: -79.99 | F8: 1063.59
A9: 46137 | B9: Apple.com/Bill | C9: Suscripciones | D9: suscripción | E9: -2.99 | F9: 1143.58
A10: 46136 | B10: Restaurante Botín | C10: Comida fuera | D10: compra | E10: -89.5 | F10: 1146.57
A11: 46135 | B11: Cepsa Av. de la Vega | C11: Combustible | D11: compra | E11: -62.8 | F11: 1236.07
A12: 46134 | B12: Carrefour Express | C12: Supermercado | D12: compra | E12: -38.75 | F12: 1298.87
A13: 46133 | B13: Ignacio Martín Ruiz | C13: Transferencias personales | D13: transferencia salida | E13: -45 | F13: 1337.62
... A42: 46113 | B42: Spotify | C42: Suscripciones | D42: suscripción | E42: -10.99 | F42: 839.01

Sheet Resumen por categoría
A1: Resumen de gasto por categoría — Abril 2026
A3: Categoría | B3: Total Gastado | C3: Nº Operaciones | D3: Importe Medio | E3: % del Gasto Total
A4: Alquiler | B4: =-SUMIFS(Movimientos!$E$2:$E$42,Movimientos!$C$2:$C$42,A4,Movimientos!$E$2:$E$42,"<0") -> 750 | C4: =COUNTIFS(Movimientos!$C$2:$C$42,A4,Movimientos!$E$2:$E$42,"<0") -> 1 | D4: =IFERROR(B4/C4,0) -> 750 | E4: =IFERROR(B4/$B$16,0) -> 0.35410765
A5: Supermercado | B5: =-SUMIFS(Movimientos!$E$2:$E$42,Movimientos!$C$2:$C$42,A5,Movimientos!$E$2:$E$42,"<0") -> 469.54 | C5: =COUNTIFS(Movimientos!$C$2:$C$42,A5,Movimientos!$E$2:$E$42,"<0") -> 9 | D5: =IFERROR(B5/C5,0) -> 52.171111 | E5: =IFERROR(B5/$B$16,0) -> 0.22169027
A6: Combustible | B6: =-SUMIFS(Movimientos!$E$2:$E$42,Movimientos!$C$2:$C$42,A6,Movimientos!$E$2:$E$42,"<0") -> 186.7 | C6: =COUNTIFS(Movimientos!$C$2:$C$42,A6,Movimientos!$E$2:$E$42,"<0") -> 3 | D6: =IFERROR(B6/C6,0) -> 62.233333 | E6: =IFERROR(B6/$B$16,0) -> 0.088149197
A7: Hogar (suministros) | B7: =-SUMIFS(Movimientos!$E$2:$E$42,Movimientos!$C$2:$C$42,A7,Movimientos!$E$2:$E$42,"<0") -> 160.45 | C7: =COUNTIFS(Movimientos!$C$2:$C$42,A7,Movimientos!$E$2:$E$42,"<0") -> 3 | D7: =IFERROR(B7/C7,0) -> 53.483333 | E7: =IFERROR(B7/$B$16,0) -> 0.07575543
A8: Comida fuera | B8: =-SUMIFS(Movimientos!$E$2:$E$42,Movimientos!$C$2:$C$42,A8,Movimientos!$E$2:$E$42,"<0") -> 153.3 | C8: =COUNTIFS(Movimientos!$C$2:$C$42,A8,Movimientos!$E$2:$E$42,"<0") -> 7 | D8: =IFERROR(B8/C8,0) -> 21.9 | E8: =IFERROR(B8/$B$16,0) -> 0.072379603
A9: Suscripciones | B9: =-SUMIFS(Movimientos!$E$2:$E$42,Movimientos!$C$2:$C$42,A9,Movimientos!$E$2:$E$42,"<0") -> 127.86 | C9: =COUNTIFS(Movimientos!$C$2:$C$42,A9,Movimientos!$E$2:$E$42,"<0") -> 6 | D9: =IFERROR(B9/C9,0) -> 21.31 | E9: =IFERROR(B9/$B$16,0) -> 0.060368272
A10: Ocio | B10: =-SUMIFS(Movimientos!$E$2:$E$42,Movimientos!$C$2:$C$42,A10,Movimientos!$E$2:$E$42,"<0") -> 98.49 | C10: =COUNTIFS(Movimientos!$C$2:$C$42,A10,Movimientos!$E$2:$E$42,"<0") -> 2 | D10: =IFERROR(B10/C10,0) -> 49.245 | E10: =IFERROR(B10/$B$16,0) -> 0.046501416
A11: Transferencias personales | B11: =-SUMIFS(Movimientos!$E$2:$E$42,Movimientos!$C$2:$C$42,A11,Movimientos!$E$2:$E$42,"<0") -> 77 | C11: =COUNTIFS(Movimientos!$C$2:$C$42,A11,Movimientos!$E$2:$E$42,"<0") -> 2 | D11: =IFERROR(B11/C11,0) -> 38.5 | E11: =IFERROR(B11/$B$16,0) -> 0.036355052
A12: Otros | B12: =-SUMIFS(Movimientos!$E$2:$E$42,Movimientos!$C$2:$C$42,A12,Movimientos!$E$2:$E$42,"<0") -> 30.4 | C12: =COUNTIFS(Movimientos!$C$2:$C$42,A12,Movimientos!$E$2:$E$42,"<0") -> 2 | D12: =IFERROR(B12/C12,0) -> 15.2 | E12: =IFERROR(B12/$B$16,0) -> 0.014353163
A13: Ropa | B13: =-SUMIFS(Movimientos!$E$2:$E$42,Movimientos!$C$2:$C$42,A13,Movimientos!$E$2:$E$42,"<0") -> 29.99 | C13: =COUNTIFS(Movimientos!$C$2:$C$42,A13,Movimientos!$E$2:$E$42,"<0") -> 1 | D13: =IFERROR(B13/C13,0) -> 29.99 | E13: =IFERROR(B13/$B$16,0) -> 0.014159585
A14: Transporte | B14: =-SUMIFS(Movimientos!$E$2:$E$42,Movimientos!$C$2:$C$42,A14,Movimientos!$E$2:$E$42,"<0") -> 21.47 | C14: =COUNTIFS(Movimientos!$C$2:$C$42,A14,Movimientos!$E$2:$E$42,"<0") -> 2 | D14: =IFERROR(B14/C14,0) -> 10.735 | E14: =IFERROR(B14/$B$16,0) -> 0.010136922
A15: Salud | B15: =-SUMIFS(Movimientos!$E$2:$E$42,Movimientos!$C$2:$C$42,A15,Movimientos!$E$2:$E$42,"<0") -> 12.8 | C15: =COUNTIFS(Movimientos!$C$2:$C$42,A15,Movimientos!$E$2:$E$42,"<0") -> 1 | D15: =IFERROR(B15/C15,0) -> 12.8 | E15: =IFERROR(B15/$B$16,0) -> 0.0060434372
A16: TOTAL | B16: =SUM(B4:B15) -> 2118 | C16: =SUM(C4:C15) -> 39 | D16: =IFERROR(B16/C16,0) -> 54.307692 | E16: =SUM(E4:E15) -> 1

Sheet Ingresos vs Gastos
A1: Ingresos vs Gastos — Abril 2026
A3: Total ingresos del mes | B3: =SUMIF(Movimientos!$E$2:$E$42,">0") -> 2250
A4: Total gastos del mes | B4: =-SUMIF(Movimientos!$E$2:$E$42,"<0") -> 2118
A5: Ahorro neto | B5: =B3-B4 -> 132
A6: Ratio ahorro / ingresos | B6: =IFERROR(B5/B3,0) -> 0.058666667

Sheet Conclusiones
A1: Conclusiones — Abril 2026
A3: Categoría con MAYOR gasto | B3: =INDEX('Resumen por categoría'!$A$4:$A$15,MATCH(MAX('Resumen por categoría'!$B$4:$B$15),'Resumen por categoría'!$B$4:$B$15,0)) -> Alquiler
A4: Importe en esa categoría | B4: =MAX('Resumen por categoría'!$B$4:$B$15) -> 750
A5: Peso sobre el gasto total | B5: =B4/'Ingresos vs Gastos'!B4 -> 0.35410765
A7: Resumen | B7: ="Donde más dinero se va este mes es a "&B3&" ("&TEXT(B4,"#,##0.00 €")&", un "&TEXT(B5,"0.0%")&" del gasto total). Es un gasto fijo difícil de tocar." -> Donde más dinero se va este mes es a Alquiler (750.00 €, un 35.4% del gasto total). Es un gasto fijo difícil de tocar.
A9: Consejo accionable | B9: ="Tienes "&B11&" suscripciones activas que suman "&TEXT(B12,"#,##0.00 €")&"/mes. La vía menos dolorosa es revisar solapes (p. ej. Amazon Prime ya incluye Prime Video, y entre Netflix y Disney+ probablemente sólo veas uno cada mes): cancelando 1-2 servicios recortas ~25-40 €/mes sin notarlo. Adicionalmente, "&TEXT(B13,"#,##0.00 €")&" en comida fuera; bajar una salida a la semana son ~25 €/mes extra ahorrados." -> Tienes 6 suscripciones activas que suman 127.86 €/mes. La vía menos dolorosa es revisar solapes (p. ej. Amazon Prime ya incluye Prime Video, y entre Netflix y Disney+ probablemente sólo veas uno cada mes): cancelando 1-2 servicios recortas ~25-40 €/mes sin notarlo. Adicionalmente, 153.30 € en comida fuera; bajar una salida a la semana son ~25 €/mes extra ahorrados.
A11: Nº de suscripciones activas | B11: =COUNTIFS(Movimientos!$D$2:$D$42,"suscripción") -> 6
A12: Gasto total en suscripciones | B12: =-SUMIFS(Movimientos!$E$2:$E$42,Movimientos!$D$2:$D$42,"suscripción") -> 127.86
A13: Gasto en comida fuera | B13: =-SUMIFS(Movimientos!$E$2:$E$42,Movimientos!$C$2:$C$42,"Comida fuera",Movimientos!$E$2:$E$42,"<0") -> 153.3
A15: Proyección anual (si abril es un mes representativo)
A16: Nómina mensual | B16: =SUMIFS(Movimientos!$E$2:$E$42,Movimientos!$D$2:$D$42,"nómina") -> 2150
A17: Ahorro neto mensual (real) | B17: ='Ingresos vs Gastos'!B5 -> 132
A18: Ahorro anual proyectado (×12) | B18: =B17*12 -> 1584
A19: Objetivo: 20% de la nómina mensual | B19: =B16*0.2 -> 430
A20: Objetivo anual (20% × nómina × 12) | B20: =B19*12 -> 5160
A21: Diferencia anual frente al objetivo | B21: =B18-B20 -> -3576
A22: Ratio de ahorro actual vs 20% | B22: =IFERROR(B17/B16,0) -> 0.061395349
A24: Veredicto | B24: ="Estás ahorrando un "&TEXT(B22,"0.0%")&" de la nómina, frente al 20% objetivo. Si sigues el ritmo de abril todo el año, ahorrarás "&TEXT(B18,"#,##0 €")&" en 12 meses; el objetivo serían "&TEXT(B20,"#,##0 €")&", así que te quedarías a "&TEXT(ABS(B21),"#,##0 €")&" del objetivo. Aplicando el consejo de arriba (recortar suscripciones + 1 cena fuera/semana) recuperas ~50-65 €/mes, ~600-780 €/año, que acortan ese hueco a la mitad." -> Estás ahorrando un 6.1% de la nómina, frente al 20% objetivo. Si sigues el ritmo de abril todo el año, ahorrarás 1,584 € en 12 meses; el objetivo serían 5,160 €, así que te quedarías a 3,576 € del objetivo. Aplicando el consejo de arriba (recortar suscripciones + 1 cena fuera/semana) recuperas ~50-65 €/mes, ~600-780 €/año, que acortan ese hueco a la mitad.
